chat_bot_sea/__init__.py
chat_bot_sea/manage.py
chat_bot_sea/config/asgi.py
chat_bot_sea/config/settings.py
chat_bot_sea/config/urls.py
chat_bot_sea/config/wsgi.py
chat_bot_sea/request_functions/item_match/bot_read_url.py
chat_bot_sea/request_functions/item_match/download_drive.py
chat_bot_sea/request_functions/item_match/build_index/func.py
chat_bot_sea/request_functions/item_match/build_index/gcp.py
chat_bot_sea/request_functions/item_match/build_index/matching_v1.py
chat_bot_sea/request_functions/item_match/build_index/matching_v2.py
chat_bot_sea/request_functions/item_match/build_index/model.py
chat_bot_sea/request_functions/item_match/testing/adhoc_v1.py
chat_bot_sea/request_functions/read_news/news.py
chat_bot_sea/request_functions/read_news/rag_web_vi.py
chat_bot_sea/seatalk/admin.py
chat_bot_sea/seatalk/apps.py
chat_bot_sea/seatalk/function_interactive.py
chat_bot_sea/seatalk/function_user.py
chat_bot_sea/seatalk/models.py
chat_bot_sea/seatalk/services.py
chat_bot_sea/seatalk/views.py
chat_bot_sea/seatalk/migrations/0001_initial.py
chat_bot_sea-0.0.1.dist-info/METADATA
chat_bot_sea-0.0.1.dist-info/WHEEL
chat_bot_sea-0.0.1.dist-info/licenses/LICENSE
chat_bot_sea-0.0.1.dist-info/RECORD
