Metadata-Version: 2.3
Name: chat_bot_sea
Version: 0.0.1
Summary: A chatbot package
Project-URL: Homepage, https://git.vndev.shopee.io/xuankhang.do/chatbot
Project-URL: Bug Tracker, https://git.vndev.shopee.io/xuankhang.do/chatbot/-/issues
Author-email: Kevin Khang <kevinkhang2909@gmail.com>
License: Copyright (c) 2023 Kevin Khang
License-File: LICENSE
Keywords: Django, chatbot
Classifier: License :: OSI Approved :: MIT License
Classifier: Operating System :: OS Independent
Classifier: Programming Language :: Python :: 3
Requires-Python: >=3.9
Requires-Dist: django
Requires-Dist: django-cors-headers
Requires-Dist: djangorestframework
Requires-Dist: loguru
Requires-Dist: requests
